{
  "rows": 40,
  "cols": 120,
  "grid": [
    "o List(./)                                                                                                              ",
    "            | a.txt                                                                                                     ",
    "                     | b.txt                                                                                            ",
    "                              `- docs/                                                                                  ",
    "                                      o Tool: running                                                                   ",
    "                                                                                                                        ",
    "                                                                                                                        ",
    "                                                                                                                        ",
    "                                                                                                                        ",
    "                                                                                                                        ",
    "                                                                                                                        ",
    "                                                                                                                        ",
    "                                                                                                                        ",
    "                                                                                                                        ",
    "                                                                                                                        ",
    "                                                                                                                        ",
    "                                                                                                                        ",
    "                                                                                                                        ",
    "                                                                                                                        ",
    "                                                                                                                        ",
    "                                                                                                                        ",
    "                                                                                                                        ",
    "                                                                                                                        ",
    "                                                                                                                        ",
    "                                                                                                                        ",
    "                                                                                                                        ",
    "                                                                                                                        ",
    "                                                                                                                        ",
    "                                                                                                                        ",
    "                                                                                                                        ",
    "                                                                                                                        ",
    "                                                                                                                        ",
    "                                                                                                                        ",
    "                                                                                                                        ",
    "                                                                                                                        ",
    "                                                                                                                        ",
    "                                                                                                                        ",
    "                                                                                                                        ",
    "                                                                                                                        ",
    "                                                                                                                        "
  ],
  "activeBuffer": "normal",
  "normalGrid": [
    "o List(./)                                                                                                              ",
    "            | a.txt                                                                                                     ",
    "                     | b.txt                                                                                            ",
    "                              `- docs/                                                                                  ",
    "                                      o Tool: running                                                                   ",
    "                                                                                                                        ",
    "                                                                                                                        ",
    "                                                                                                                        ",
    "                                                                                                                        ",
    "                                                                                                                        ",
    "                                                                                                                        ",
    "                                                                                                                        ",
    "                                                                                                                        ",
    "                                                                                                                        ",
    "                                                                                                                        ",
    "                                                                                                                        ",
    "                                                                                                                        ",
    "                                                                                                                        ",
    "                                                                                                                        ",
    "                                                                                                                        ",
    "                                                                                                                        ",
    "                                                                                                                        ",
    "                                                                                                                        ",
    "                                                                                                                        ",
    "                                                                                                                        ",
    "                                                                                                                        ",
    "                                                                                                                        ",
    "                                                                                                                        ",
    "                                                                                                                        ",
    "                                                                                                                        ",
    "                                                                                                                        ",
    "                                                                                                                        ",
    "                                                                                                                        ",
    "                                                                                                                        ",
    "                                                                                                                        ",
    "                                                                                                                        ",
    "                                                                                                                        ",
    "                                                                                                                        ",
    "                                                                                                                        ",
    "                                                                                                                        "
  ],
  "alternateGrid": [
    "                                                                                                                        ",
    "                                                                                                                        ",
    "                                                                                                                        ",
    "                                                                                                                        ",
    "                                                                                                                        ",
    "                                                                                                                        ",
    "                                                                                                                        ",
    "                                                                                                                        ",
    "                                                                                                                        ",
    "                                                                                                                        ",
    "                                                                                                                        ",
    "                                                                                                                        ",
    "                                                                                                                        ",
    "                                                                                                                        ",
    "                                                                                                                        ",
    "                                                                                                                        ",
    "                                                                                                                        ",
    "                                                                                                                        ",
    "                                                                                                                        ",
    "                                                                                                                        ",
    "                                                                                                                        ",
    "                                                                                                                        ",
    "                                                                                                                        ",
    "                                                                                                                        ",
    "                                                                                                                        ",
    "                                                                                                                        ",
    "                                                                                                                        ",
    "                                                                                                                        ",
    "                                                                                                                        ",
    "                                                                                                                        ",
    "                                                                                                                        ",
    "                                                                                                                        ",
    "                                                                                                                        ",
    "                                                                                                                        ",
    "                                                                                                                        ",
    "                                                                                                                        ",
    "                                                                                                                        ",
    "                                                                                                                        ",
    "                                                                                                                        ",
    "                                                                                                                        "
  ],
  "timestamp": 1770868112446
}
