{"$id":"https://breadboard.dev/contracts/public/schemas/bb.claim_reverification_report.v1.schema.json","$schema":"https://json-schema.org/draft/2020-12/schema","additionalProperties":false,"properties":{"checked_at":{"format":"date-time","type":"string"},"claim_id":{"minLength":1,"type":"string"},"comparator_rerun":{"type":"boolean"},"errors":{"items":{"minLength":1,"type":"string"},"type":"array"},"mode":{"const":"check_only"},"ok":{"type":"boolean"},"schema_version":{"const":"bb.claim_reverification_report.v1"}},"required":["schema_version","ok","errors","claim_id","mode","comparator_rerun","checked_at"],"title":"BreadBoard candidate claim reverification report V1","type":"object"}
